{"mean":{"confidence_interval":{"confidence_level":0.95,"lower_bound":7203.938837798035,"upper_bound":7264.328485246543},"point_estimate":7233.872614224222,"standard_error":15.361752980751804},"median":{"confidence_interval":{"confidence_level":0.95,"lower_bound":7189.834996436208,"upper_bound":7264.210313343017},"point_estimate":7223.435349017444,"standard_error":18.13250341048204},"median_abs_dev":{"confidence_interval":{"confidence_level":0.95,"lower_bound":120.5586990071959,"upper_bound":203.59679920058443},"point_estimate":161.30333482377137,"standard_error":21.019772936255983},"slope":{"confidence_interval":{"confidence_level":0.95,"lower_bound":7217.562647148066,"upper_bound":7298.423506868869},"point_estimate":7258.174790800098,"standard_error":20.66933878161682},"std_dev":{"confidence_interval":{"confidence_level":0.95,"lower_bound":132.8988066374854,"upper_bound":173.77683208889357},"point_estimate":154.21993487023954,"standard_error":10.454787883358545}}